sterik/Configs.py
sterik/__init__.py
sterik/encryption.py
sterik/rubika.py
sterik/socket.py
sterik/url.py
sterik-1.0.2.dist-info/LICENCE
sterik-1.0.2.dist-info/METADATA
sterik-1.0.2.dist-info/WHEEL
sterik-1.0.2.dist-info/top_level.txt
sterik-1.0.2.dist-info/RECORD
